{
  "requests_remaining": 380,
  "requests_used": 564,
  "last_updated": "2026-03-24T22:30:25.026593+00:00",
  "billing_period_start": "2026-03",
  "call_log": [
    {
      "ts": "2026-03-18T16:32:26.992745+00:00",
      "endpoint": "odds/games",
      "remaining": 491
    },
    {
      "ts": "2026-03-18T16:32:27.603085+00:00",
      "endpoint": "odds/games",
      "remaining": 488
    },
    {
      "ts": "2026-03-18T22:07:15.422615+00:00",
      "endpoint": "odds/games",
      "remaining": 413
    },
    {
      "ts": "2026-03-18T22:07:15.916638+00:00",
      "endpoint": "odds/games",
      "remaining": 410
    },
    {
      "ts": "2026-03-18T22:11:15.965529+00:00",
      "endpoint": "odds/games",
      "remaining": 407
    },
    {
      "ts": "2026-03-18T22:11:17.101883+00:00",
      "endpoint": "odds/games",
      "remaining": 404
    },
    {
      "ts": "2026-03-18T22:27:41.305529+00:00",
      "endpoint": "odds/games",
      "remaining": 401
    },
    {
      "ts": "2026-03-18T22:27:41.814673+00:00",
      "endpoint": "odds/games",
      "remaining": 398
    },
    {
      "ts": "2026-03-18T22:46:07.179212+00:00",
      "endpoint": "odds/games",
      "remaining": 395
    },
    {
      "ts": "2026-03-18T22:46:07.733714+00:00",
      "endpoint": "odds/games",
      "remaining": 392
    },
    {
      "ts": "2026-03-18T23:00:33.388174+00:00",
      "endpoint": "odds/games",
      "remaining": 389
    },
    {
      "ts": "2026-03-18T23:00:36.353035+00:00",
      "endpoint": "odds/games",
      "remaining": 386
    },
    {
      "ts": "2026-03-19T01:15:56.393941+00:00",
      "endpoint": "odds/games",
      "remaining": 353
    },
    {
      "ts": "2026-03-19T01:16:04.584855+00:00",
      "endpoint": "odds/games",
      "remaining": 350
    },
    {
      "ts": "2026-03-19T14:19:04.264377+00:00",
      "endpoint": "odds/games",
      "remaining": 281
    },
    {
      "ts": "2026-03-19T14:19:04.756012+00:00",
      "endpoint": "odds/games",
      "remaining": 278
    },
    {
      "ts": "2026-03-19T16:27:46.976192+00:00",
      "endpoint": "odds/games",
      "remaining": 275
    },
    {
      "ts": "2026-03-19T16:27:47.461754+00:00",
      "endpoint": "odds/games",
      "remaining": 272
    },
    {
      "ts": "2026-03-19T22:05:01.238145+00:00",
      "endpoint": "odds/games",
      "remaining": 197
    },
    {
      "ts": "2026-03-19T22:05:02.230771+00:00",
      "endpoint": "odds/games",
      "remaining": 194
    },
    {
      "ts": "2026-03-19T22:08:41.099802+00:00",
      "endpoint": "odds/games",
      "remaining": 191
    },
    {
      "ts": "2026-03-19T22:08:41.655316+00:00",
      "endpoint": "odds/games",
      "remaining": 188
    },
    {
      "ts": "2026-03-19T22:26:41.995381+00:00",
      "endpoint": "odds/games",
      "remaining": 185
    },
    {
      "ts": "2026-03-19T22:26:42.631457+00:00",
      "endpoint": "odds/games",
      "remaining": 182
    },
    {
      "ts": "2026-03-19T22:45:35.744794+00:00",
      "endpoint": "odds/games",
      "remaining": 173
    },
    {
      "ts": "2026-03-19T22:45:36.402573+00:00",
      "endpoint": "odds/games",
      "remaining": 170
    },
    {
      "ts": "2026-03-19T22:59:34.344826+00:00",
      "endpoint": "odds/games",
      "remaining": 167
    },
    {
      "ts": "2026-03-19T22:59:34.796249+00:00",
      "endpoint": "odds/games",
      "remaining": 164
    },
    {
      "ts": "2026-03-20T14:16:22.240488+00:00",
      "endpoint": "odds/games",
      "remaining": 59
    },
    {
      "ts": "2026-03-20T14:16:23.077026+00:00",
      "endpoint": "odds/games",
      "remaining": 56
    },
    {
      "ts": "2026-03-20T16:21:22.705049+00:00",
      "endpoint": "odds/games",
      "remaining": 50
    },
    {
      "ts": "2026-03-20T16:21:23.638434+00:00",
      "endpoint": "odds/games",
      "remaining": 47
    },
    {
      "ts": "2026-03-22T03:34:01.078472+00:00",
      "endpoint": "odds/games",
      "remaining": 491
    },
    {
      "ts": "2026-03-22T03:34:01.644083+00:00",
      "endpoint": "odds/games",
      "remaining": 488
    },
    {
      "ts": "2026-03-22T14:08:50.418620+00:00",
      "endpoint": "odds/games",
      "remaining": 485
    },
    {
      "ts": "2026-03-22T14:08:51.149849+00:00",
      "endpoint": "odds/games",
      "remaining": 482
    },
    {
      "ts": "2026-03-22T16:13:05.898694+00:00",
      "endpoint": "odds/games",
      "remaining": 479
    },
    {
      "ts": "2026-03-22T16:13:06.488006+00:00",
      "endpoint": "odds/games",
      "remaining": 476
    },
    {
      "ts": "2026-03-22T22:04:38.949796+00:00",
      "endpoint": "odds/games",
      "remaining": 473
    },
    {
      "ts": "2026-03-22T22:04:39.527765+00:00",
      "endpoint": "odds/games",
      "remaining": 470
    },
    {
      "ts": "2026-03-22T22:08:07.357070+00:00",
      "endpoint": "odds/games",
      "remaining": 467
    },
    {
      "ts": "2026-03-22T22:08:08.114719+00:00",
      "endpoint": "odds/games",
      "remaining": 464
    },
    {
      "ts": "2026-03-22T22:25:53.637885+00:00",
      "endpoint": "odds/games",
      "remaining": 461
    },
    {
      "ts": "2026-03-22T22:25:54.373537+00:00",
      "endpoint": "odds/games",
      "remaining": 458
    },
    {
      "ts": "2026-03-22T22:43:31.888079+00:00",
      "endpoint": "odds/games",
      "remaining": 455
    },
    {
      "ts": "2026-03-22T22:43:32.622399+00:00",
      "endpoint": "odds/games",
      "remaining": 452
    },
    {
      "ts": "2026-03-22T22:56:39.253994+00:00",
      "endpoint": "odds/games",
      "remaining": 449
    },
    {
      "ts": "2026-03-22T22:56:39.840261+00:00",
      "endpoint": "odds/games",
      "remaining": 446
    },
    {
      "ts": "2026-03-23T14:25:22.669838+00:00",
      "endpoint": "odds/games",
      "remaining": 443
    },
    {
      "ts": "2026-03-23T14:25:23.262870+00:00",
      "endpoint": "odds/games",
      "remaining": 440
    },
    {
      "ts": "2026-03-23T16:28:04.562875+00:00",
      "endpoint": "odds/games",
      "remaining": 437
    },
    {
      "ts": "2026-03-23T16:28:05.167957+00:00",
      "endpoint": "odds/games",
      "remaining": 434
    },
    {
      "ts": "2026-03-23T22:06:50.077725+00:00",
      "endpoint": "odds/games",
      "remaining": 431
    },
    {
      "ts": "2026-03-23T22:06:50.700921+00:00",
      "endpoint": "odds/games",
      "remaining": 428
    },
    {
      "ts": "2026-03-23T22:17:00.948328+00:00",
      "endpoint": "odds/games",
      "remaining": 425
    },
    {
      "ts": "2026-03-23T22:17:01.645286+00:00",
      "endpoint": "odds/games",
      "remaining": 422
    },
    {
      "ts": "2026-03-23T22:33:29.918677+00:00",
      "endpoint": "odds/games",
      "remaining": 419
    },
    {
      "ts": "2026-03-23T22:33:30.663932+00:00",
      "endpoint": "odds/games",
      "remaining": 416
    },
    {
      "ts": "2026-03-23T22:58:16.360603+00:00",
      "endpoint": "odds/games",
      "remaining": 413
    },
    {
      "ts": "2026-03-23T22:58:17.091940+00:00",
      "endpoint": "odds/games",
      "remaining": 410
    },
    {
      "ts": "2026-03-24T14:26:33.793751+00:00",
      "endpoint": "odds/games",
      "remaining": 407
    },
    {
      "ts": "2026-03-24T14:26:34.545993+00:00",
      "endpoint": "odds/games",
      "remaining": 404
    },
    {
      "ts": "2026-03-24T16:31:12.783933+00:00",
      "endpoint": "odds/games",
      "remaining": 401
    },
    {
      "ts": "2026-03-24T16:31:13.451213+00:00",
      "endpoint": "odds/games",
      "remaining": 398
    },
    {
      "ts": "2026-03-24T22:08:22.495593+00:00",
      "endpoint": "odds/games",
      "remaining": 395
    },
    {
      "ts": "2026-03-24T22:08:23.056884+00:00",
      "endpoint": "odds/games",
      "remaining": 392
    },
    {
      "ts": "2026-03-24T22:14:46.889445+00:00",
      "endpoint": "odds/games",
      "remaining": 389
    },
    {
      "ts": "2026-03-24T22:14:47.473813+00:00",
      "endpoint": "odds/games",
      "remaining": 386
    },
    {
      "ts": "2026-03-24T22:30:24.249116+00:00",
      "endpoint": "odds/games",
      "remaining": 383
    },
    {
      "ts": "2026-03-24T22:30:25.026593+00:00",
      "endpoint": "odds/games",
      "remaining": 380
    }
  ]
}