{"year": 2026, "num_simulations": 10000, "champion_probs": {"Arizona": 0.2644, "Michigan": 0.1976, "Duke": 0.1711, "Florida": 0.0948, "Purdue": 0.069, "Illinois": 0.0644, "Houston": 0.0619, "Iowa St.": 0.0301, "Texas Tech": 0.0055, "Kansas": 0.0053, "Vanderbilt": 0.0046, "Connecticut": 0.0045, "Tennessee": 0.0042, "Virginia": 0.0041, "St. John's": 0.0039, "Michigan St.": 0.0032, "Louisville": 0.0027, "Gonzaga": 0.0022, "Wisconsin": 0.0014, "Arkansas": 0.0012, "Ohio St.": 0.0011, "Nebraska": 0.0011, "UCLA": 0.001, "Alabama": 0.0003, "Kentucky": 0.0002, "Texas": 0.0001, "Utah St.": 0.0001}, "final_four_probs": {"Arizona": 0.6503, "Michigan": 0.6043, "Duke": 0.5531, "Florida": 0.3637, "Illinois": 0.2932, "Purdue": 0.2683, "Houston": 0.2526, "Iowa St.": 0.1869, "Connecticut": 0.0841, "Michigan St.": 0.0836, "St. John's": 0.0687, "Tennessee": 0.0663, "Kansas": 0.0654, "Louisville": 0.0644, "Texas Tech": 0.0642, "Virginia": 0.057, "Vanderbilt": 0.0561, "UCLA": 0.0502, "Gonzaga": 0.0377, "Ohio St.": 0.0293, "Nebraska": 0.0256, "Arkansas": 0.0202, "Wisconsin": 0.0176, "Alabama": 0.0125, "Iowa": 0.0053, "Kentucky": 0.005, "Utah St.": 0.0023, "Santa Clara": 0.0022, "Saint Mary's": 0.0019, "Georgia": 0.0015, "Texas": 0.001, "Missouri": 0.0009, "Miami FL": 0.0009, "Clemson": 0.0008, "TCU": 0.0006, "Villanova": 0.0006, "North Carolina": 0.0003, "Texas A&M": 0.0003, "South Florida": 0.0003, "UCF": 0.0002, "BYU": 0.0002, "VCU": 0.0002, "Cal Baptist": 0.0001, "Saint Louis": 0.0001}, "elite_eight_probs": {"Arizona": 0.8678, "Michigan": 0.8107, "Purdue": 0.7413, "Florida": 0.6961, "Duke": 0.6714, "Illinois": 0.5421, "Iowa St.": 0.4862, "Houston": 0.4333, "Connecticut": 0.287, "Michigan St.": 0.2599, "Tennessee": 0.2495, "Louisville": 0.2353, "Virginia": 0.2122, "Gonzaga": 0.2071, "UCLA": 0.2061, "Vanderbilt": 0.1601, "Texas Tech": 0.1397, "St. John's": 0.1383, "Kansas": 0.133, "Nebraska": 0.1068, "Arkansas": 0.0678, "Ohio St.": 0.0537, "Wisconsin": 0.051, "Alabama": 0.0404, "Kentucky": 0.0309, "Iowa": 0.0294, "Santa Clara": 0.021, "Miami FL": 0.0149, "Texas": 0.014, "Saint Mary's": 0.0131, "BYU": 0.0119, "Missouri": 0.0108, "Utah St.": 0.0093, "Clemson": 0.0075, "Georgia": 0.0066, "UCF": 0.0066, "South Florida": 0.0051, "North Carolina": 0.0048, "Texas A&M": 0.0039, "Villanova": 0.0038, "TCU": 0.0029, "VCU": 0.0028, "Saint Louis": 0.0024, "Northern Iowa": 0.0006, "Miami OH": 0.0002, "Akron": 0.0002, "High Point": 0.0002, "Cal Baptist": 0.0001, "McNeese St.": 0.0001, "Hawaii": 0.0001}, "sweet_sixteen_probs": {"Michigan": 0.9626, "Arizona": 0.9585, "Illinois": 0.9338, "Purdue": 0.9229, "Florida": 0.9009, "Houston": 0.8884, "Duke": 0.8745, "Iowa St.": 0.8419, "Gonzaga": 0.7415, "Texas Tech": 0.6098, "Arkansas": 0.5821, "Connecticut": 0.5662, "Michigan St.": 0.5325, "Tennessee": 0.5286, "Vanderbilt": 0.5238, "St. John's": 0.5217, "Virginia": 0.4692, "Nebraska": 0.4671, "Kansas": 0.4652, "Louisville": 0.4396, "Wisconsin": 0.4134, "UCLA": 0.3982, "Alabama": 0.3788, "Texas": 0.1298, "BYU": 0.1278, "Ohio St.": 0.1117, "Kentucky": 0.0863, "Santa Clara": 0.0718, "Saint Mary's": 0.0685, "Iowa": 0.0673, "Miami FL": 0.0447, "Texas A&M": 0.0428, "North Carolina": 0.0409, "UCF": 0.0356, "Missouri": 0.0324, "Clemson": 0.0318, "Georgia": 0.0266, "South Florida": 0.0264, "Utah St.": 0.0252, "VCU": 0.0252, "Villanova": 0.0163, "TCU": 0.0138, "Saint Louis": 0.0108, "Northern Iowa": 0.0102, "McNeese St.": 0.0087, "Akron": 0.0076, "Hofstra": 0.0038, "High Point": 0.0038, "Cal Baptist": 0.0029, "Miami OH": 0.002, "North Dakota St.": 0.0015, "Kennesaw St.": 0.0009, "Hawaii": 0.0007, "Troy": 0.0004, "Idaho": 0.0003, "Wright St.": 0.0002, "Penn": 0.0001}, "round_of_32_probs": {"Michigan": 0.9996, "Florida": 0.9995, "Duke": 0.9992, "Purdue": 0.9992, "Iowa St.": 0.9989, "Illinois": 0.9984, "Arizona": 0.9981, "Houston": 0.9975, "Connecticut": 0.9909, "Gonzaga": 0.9862, "Virginia": 0.9852, "Nebraska": 0.9772, "Michigan St.": 0.9728, "Arkansas": 0.9693, "Kansas": 0.9574, "Wisconsin": 0.9525, "Tennessee": 0.9476, "Texas Tech": 0.943, "Vanderbilt": 0.9368, "Alabama": 0.9362, "St. John's": 0.9112, "Louisville": 0.8299, "UCLA": 0.7848, "Ohio St.": 0.7484, "Georgia": 0.6002, "Iowa": 0.5747, "BYU": 0.5525, "Utah St.": 0.5346, "Santa Clara": 0.5166, "Saint Mary's": 0.5107, "North Carolina": 0.5078, "Miami FL": 0.5036, "Missouri": 0.4964, "VCU": 0.4922, "Texas A&M": 0.4893, "Kentucky": 0.4834, "Villanova": 0.4654, "Texas": 0.4475, "Clemson": 0.4253, "Saint Louis": 0.3998, "TCU": 0.2516, "UCF": 0.2152, "South Florida": 0.1701, "Northern Iowa": 0.0888, "Hofstra": 0.0638, "McNeese St.": 0.0632, "Akron": 0.057, "Miami OH": 0.0524, "High Point": 0.0475, "Cal Baptist": 0.0426, "Hawaii": 0.0307, "North Dakota St.": 0.0272, "Troy": 0.0228, "Wright St.": 0.0148, "Kennesaw St.": 0.0138, "Furman": 0.0091, "Idaho": 0.0025, "Long Island": 0.0019, "Penn": 0.0016, "Tennessee St.": 0.0011, "Siena": 0.0008, "Queens": 0.0008, "Prairie View A&M": 0.0005, "UMBC": 0.0004}}